{
  "build": {
    "beforeDevCommand": "npm run dev",
    "beforeBuildCommand": "npm run build",
    "devPath": "http://localhost:5173",
    "distDir": "../dist",
    "withGlobalTauri": true
  },
  "package": {
    "productName": "sistema-hospitalario-ads",
    "version": "2.5.0"
  },
  "tauri": {
    "allowlist": {
      "all": true,
      "shell": {
        "all": true,
        "open": true
      },
      "dialog": {
        "all": true
      },
      "fs": {
        "all": true,
        "scope": ["$APP/*", "$DESKTOP/*", "$DOCUMENT/*"]
      },
      "path": {
        "all": true
      },
      "protocol": {
        "asset": true,
        "assetScope": ["**"]
      }
    },
    "bundle": {
      "active": true,
      "category": "Medical",
      "copyright": "",
      "deb": {
        "depends": []
      },
      "externalBin": [],
      "icon": [
        "icons/32x32.png",
        "icons/128x128.png",
        "icons/128x128@2x.png",
        "icons/icon.icns",
        "icons/icon.ico"
      ],
      "identifier": "com.sistema-hospitalario.ads",
      "longDescription": "",
      "macOS": {
        "entitlements": null,
        "exceptionDomain": "",
        "frameworks": [],
        "providerShortName": null,
        "signingIdentity": null
      },
      "resources": [],
      "shortDescription": "",
      "targets": "all",
      "windows": {
        "certificateThumbprint": null,
        "digestAlgorithm": "sha256",
        "timestampUrl": ""
      }
    },
    "security": {
      "csp": null
    },
    "updater": {
      "active": false
    },
    "windows": [
      {
        "fullscreen": false,
        "height": 800,
        "resizable": true,
        "title": "Sistema Hospitalario ADS",
        "width": 1200
      }
    ]
  }
}